py_adquality/__init__.py
py_adquality/pyquality.py
py_quality-0.0.5.dist-info/LICENSE
py_quality-0.0.5.dist-info/METADATA
py_quality-0.0.5.dist-info/WHEEL
py_quality-0.0.5.dist-info/top_level.txt
py_quality-0.0.5.dist-info/RECORD
